{
  "project_info": {
    "project_number": "78907589016",
    "project_id": "sullacorbetta-86407",
    "storage_bucket": "sullacorbetta-86407.firebasestorage.app"
  },
  "client": [
    {
      "client_info": {
        "mobilesdk_app_id": "1:78907589016:android:fa066c499f8a66420a6bed",
        "android_client_info": {
          "package_name": "com.example.flutter_application_1"
        }
      },
      "oauth_client": [],
      "api_key": [
        {
          "current_key": "AIzaSyC6jkGdPyvqsEQcQo3G39hvxbOKsUq8YEo"
        }
      ],
      "services": {
        "appinvite_service": {
          "other_platform_oauth_client": []
        }
      }
    }
  ],
  "configuration_version": "1"
}